tricky/__init__.py
tricky/getters.py
tricky/iterables.py
tricky/pydantic/__init__.py
tricky/pydantic/mutators.py
tricky/pydantic/types.py
tricky/typing.py
tricky/utils/__init__.py
tricky/utils/decorators.py
tricky-0.0.16.dist-info/LICENSE
tricky-0.0.16.dist-info/METADATA
tricky-0.0.16.dist-info/WHEEL
tricky-0.0.16.dist-info/RECORD
